{
  "type":"FeatureCollection",
  "features":[
    {
      "type":"Feature",
      "bbox":[
        27.019187,
        53.625823,
        27.96249,
        54.254909
      ],
      "geometry":{
        "coordinates":[
          27.234342,
          53.940465
        ],
        "type":"Point"
      },
      "properties":{
        "feature_name":"Minsk",
        "matching_name":"Minsk",
        "description":"Minsk Region, Belarus, Planet Earth",
        "place_name":"Minsk, Minsk Region, Belarus",
        "id":"place.11543680732831130",
        "place_type":[
          "place",
          "region"
        ],
        "context":[
          {
            "layer":"address",
            "name":"Minsk Region, Belarus"
          },
          {
            "layer":"region.14146701401889110",
            "name":"Minsk Region"
          },
          {
            "layer":"country.13685961050877970",
            "name":"Belarus"
          }
        ],
        "language":"en",
        "maki":"marker",
        "internal_id":"Y2WAgIKcxORUAA==.Y2OAgOTEotzUPAA=.RcwxDsIwDAVQjoI89wSM7CxcAKWJ1VqkNrKdoUIchpsSMFW9vf-__D7EPSFLY9cVTnDGmrQZDKA4kXCPLsR2P16DAxQyV8rem65HTRm30ddinqVgtFVyquRriJGmeRSdRUokqRRFsx03bsuI-t-n5ffn9QE=",
        "external_ids":{
          "carmen":"place.11543680732831130"
        },
        "accuracy": "rooftop",
        "metadata":{
          "iso_3166_1":"by",
          "iso_3166_2":"BY-MI",
          "average_rating":4.0,
          "website":"https://www.starbucks.com/store-locator/store/7373/shoreline-pear-1380-pear-avenue-mountain-view-ca-940431360-us",
          "phone":"+1 650-965-2048",
          "review_count":17,
          "detailed_description":"Starbucks, Mountain View",
          "primary_photo":[
            {
              "width":50,
              "height":50,
              "url":"http://media-cdn.tripadvisor.com/media/photo-t/18/47/98/c6/starbucks-inside-and.jpg"
            },
            {
              "width":150,
              "height":150,
              "url":"http://media-cdn.tripadvisor.com/media/photo-l/18/47/98/c6/starbucks-inside-and.jpg"
            },
            {
              "width":1708,
              "height":2046,
              "url":"http://media-cdn.tripadvisor.com/media/photo-o/18/47/98/c6/starbucks-inside-and.jpg"
            }
          ],
          "open_hours": {
            "open_type": "AlwaysOpen"
          },
          "cps": {
            "raw": {
            }
          },
          "parking": {
            "capacity": 20,
            "reserved_for_disabilities": 2,
            "levels": 2
          }
        },
        "routable_points": [
          {
            "name": "City Entrance",
            "coordinates": [
              27.234300,
              53.973651
            ]
          }
        ]
      }
    }
  ],
  "attribution":"© 2021 Mapbox and its suppliers. All rights reserved. Use of this data is subject to the Mapbox Terms of Service. (https://www.mapbox.com/about/maps/)",
  "version":"12:9476295bf0515457bd2a576af2b1d06d3bf42a57",
  "response_uuid":"0a197057-edf0-4447-be63-9badcf7c19be"
}
